README.md
setup.py
bstops/__init__.py
bstops/security/__init__.py
bstops/security/pass64.py
bstops/security/totp.py
bstops_security.egg-info/PKG-INFO
bstops_security.egg-info/SOURCES.txt
bstops_security.egg-info/dependency_links.txt
bstops_security.egg-info/requires.txt
bstops_security.egg-info/top_level.txt