Metadata-Version: 1.0
Name: bstops-security
Version: 0.0.1
Summary: Security package
Home-page: https://github.com/viger1228/bstops-security
Author: walker
Author-email: walkerIVI@gmail.com
License: MIT Licence
Keywords: pip,bstops,security
Platform: any
